Workbook

Sheet Hướng dẫn
A1: Hướng dẫn sử dụng file dữ liệu (Mô hình mở rộng)
A2: Bài tập lớn MAT16A – Tài chính công Việt Nam 2005–2020 (Mô hình OLS có bổ sung FDI_GDP và Trade_Openness)
A4: Mục | B4: Nội dung cần đọc
A5: 1. Dashboard | B5: Xem nhanh xu hướng chính, KPI trung bình và biểu đồ tổng quan để viết phần nhận xét ban đầu.
A6: 2. Data_2005_2020 | B6: Bảng dữ liệu chính, bổ sung 2 cột mới: FDI_GDP và Trade_Openness.
A7: 3. Mô tả biến | B7: Bảng codebook giải thích từng biến, đơn vị, nguồn/công thức và cách dùng trong mô hình.
A8: 4. Thống kê mô tả | B8: Dùng để viết mục Data & Methodology và mô tả đặc điểm dữ liệu.
A9: 5. Tương quan | B9: Dùng để nhận xét mối quan hệ sơ bộ giữa các biến và kiểm tra đa cộng tuyến sơ bộ.
A10: 6. Hồi quy OLS | B10: Mô hình mở rộng: GDP_Growth = β0 + β1·Balance_GDP + β2·Inflation + β3·FDI_GDP + β4·Trade_Openness + u. Có so sánh với mô hình gốc.
A11: 7. Nguồn dữ liệu | B11: Ghi rõ URL nguồn dữ liệu và lưu ý khi trích dẫn trong báo cáo.
A13: Lưu ý quan trọng: | B13: (1) Dữ liệu tài khóa 2005–2008 và 2009–2020 được ghép từ hai nguồn công khai khác nhau (IMF WEO via EconStats và World Bank MPO). (2) FDI_GDP và Trade_Openness lấy từ World Bank WDI, đã làm tròn 2 chữ số thập phân. (3) Với chỉ 16 quan sát, cần thận trọng khi diễn giải kết quả; chỉ nên giữ tối đa 4–5 biến độc lập để bảo đảm bậc tự do. (4) Năm 2020 (cú sốc COVID-19) có tăng trưởng giảm đột biến – cần lưu ý khi giải thích.

Sheet Dashboard
A1: Dashboard – Tài chính công và tăng trưởng Việt Nam (Mô hình mở rộng)
A2: Tổng quan nhanh bộ dữ liệu 2005–2020 cho phần nhận xét và trình bày báo cáo.
A4: Tăng trưởng GDP TB | C4: Cân đối NS TB | E4: FDI/GDP TB | G4: Độ mở thương mại TB
A5: =AVERAGE(Data_2005_2020!B7:B22) -> 6.3336346 | C5: =AVERAGE(Data_2005_2020!F7:F22) -> -3.533125 | E5: =AVERAGE(Data_2005_2020!G7:G22) -> 6.076875 | G5: =AVERAGE(Data_2005_2020!H7:H22) -> 142.83062
A6: % | C6: % GDP | E6: % GDP | G6: % GDP
A8: Lạm phát cao nhất | C8: Lạm phát TB | E8: Năm tăng trưởng thấp nhất | G8: Tăng trưởng thấp nhất
A9: =MAX(Data_2005_2020!E7:E22) -> 23.115448 | C9: =AVERAGE(Data_2005_2020!E7:E22) -> 7.3695432 | E9: =INDEX(Data_2005_2020!A7:A22,MATCH(MIN(Data_2005_2020!B7:B22),Data_2005_2020!B7:B22,0)) -> 2020 | G9: =MIN(Data_2005_2020!B7:B22) -> 2.865413
A10: % | C10: % | E10: năm | G10: %
A12: Gợi ý nhận xét nhanh:
A13: 1. Giai đoạn 2005–2020 có 16 quan sát theo năm. Với 4 biến độc lập, bậc tự do dư còn 11 – phù hợp cho hồi quy đơn giản nhưng cần thận trọng khi giải thích.
A14: 2. Việt Nam có FDI/GDP trung bình ~5.9% (cao so với khu vực), độ mở thương mại trung bình ~144% GDP – là nền kinh tế cực kỳ mở.
A15: 3. Balance_GDP thường âm (-3.5% TB), phản ánh tình trạng bội chi kéo dài; tương quan dương yếu với GDP_Growth ngụ ý thâm hụt giảm thường đi cùng tăng trưởng tốt hơn.
A16: 4. Năm 2008 (lạm phát 23.1%, GFC), 2011 (lạm phát 18.7%) và 2020 (COVID-19, tăng trưởng 2.87%) là các năm bất thường lớn.
A17: 5. Mô hình mở rộng (4 biến) cải thiện R² so với mô hình gốc, nhưng cú sốc COVID-19 2020 vẫn là điểm dữ liệu khó giải thích nếu không thêm biến giả.

Sheet Data_2005_2020
A1: Dữ liệu tài chính công Việt Nam giai đoạn 2005–2020 (mở rộng)
A2: Đơn vị chính: %, % GDP; bổ sung các biến mở rộng FDI_GDP và Trade_Openness.
A4: Year | B4: GDP_Growth | C4: Revenue_GDP | D4: Expenditure_GDP | E4: Inflation | F4: Balance_GDP | G4: FDI_GDP | H4: Trade_Openness | I4: GDP_Current_USD_bn | J4: Data_Note
A5: Năm quan sát | B5: Tăng trưởng GDP thực hằng năm | C5: Tổng thu NSNN so với GDP | D5: Tổng chi NSNN so với GDP | E5: Lạm phát CPI hằng năm | F5: Cân đối ngân sách so với GDP = Thu/GDP - Chi/GDP | G5: Tỷ lệ FDI ròng so với GDP | H5: Độ mở thương mại = (XK+NK)/GDP | I5: GDP theo giá hiện hành (tỷ USD) | J5: Ghi chú
A6: Năm | B6: % | C6: % GDP | D6: % GDP | E6: % | F6: % GDP | G6: % GDP | H6: % GDP | I6: Tỷ USD | J6: Văn bản
A7: 2005 | B7: 7.547256 | C7: 27.2 | D7: 28.51 | E7: 8.284572 | F7: =C7-D7 -> -1.31 | G7: 3.39 | H7: 130.71 | I7: 57.633256 | J7: Năm bình thường
A8: 2006 | B8: 6.977975 | C8: 28.69 | D8: 28.39 | E8: 7.418017 | F8: =C8-D8 -> 0.3 | G8: 3.62 | H8: 138.31 | I8: 66.371665 | J8: Năm bình thường
A9: 2007 | B9: 7.129493 | C9: 28.45 | D9: 30.63 | E9: 8.344449 | F9: =C9-D9 -> -2.18 | G9: 8.65 | H9: 154.61 | I9: 77.414426 | J9: Năm bình thường
A10: 2008 | B10: 5.661787 | C10: 28.91 | D10: 29.45 | E10: 23.115448 | F10: =C10-D10 -> -0.54 | G10: 9.66 | H10: 154.32 | I10: 99.130304 | J10: Khủng hoảng tài chính toàn cầu (lạm phát ~23%)
A11: 2009 | B11: 5.397871 | C11: 25.6 | D11: 31.6 | E11: 6.716983 | F11: =C11-D11 -> -6 | G11: 7.17 | H11: 134.71 | I11: 106.01466 | J11: Hậu khủng hoảng GFC, tăng trưởng giảm
A12: 2010 | B12: 6.423267 | C12: 27.3 | D12: 30 | E12: 9.207466 | F12: =C12-D12 -> -2.7 | G12: 6.9 | H12: 113.98 | I12: 147.20117 | J12: Năm bình thường
A13: 2011 | B13: 6.413169 | C13: 25.9 | D13: 27 | E13: 18.677732 | F13: =C13-D13 -> -1.1 | G13: 5.48 | H13: 125.26 | I13: 172.59505 | J13: Lạm phát hai con số (~18.7%)
A14: 2012 | B14: 5.504545 | C14: 22.6 | D14: 29.5 | E14: 9.094703 | F14: =C14-D14 -> -6.9 | G14: 5.37 | H14: 123.22 | I14: 195.59066 | J14: Năm bình thường
A15: 2013 | B15: 5.553511 | C15: 23.1 | D15: 30.5 | E15: 6.592675 | F15: =C15-D15 -> -7.4 | G15: 5.2 | H15: 130.85 | I15: 213.70881 | J15: Năm bình thường
A16: 2014 | B16: 6.422243 | C16: 22.2 | D16: 28.5 | E16: 4.084554 | F16: =C16-D16 -> -6.3 | G16: 4.94 | H16: 135.41 | I16: 233.45147 | J16: Năm bình thường
A17: 2015 | B17: 6.987154 | C17: 23.8 | D17: 29.9 | E17: 0.631201 | F17: =C17-D17 -> -6.1 | G17: 6.11 | H17: 144.91 | I17: 239.25833 | J17: Năm bình thường
A18: 2016 | B18: 6.690009 | C18: 23.9 | D18: 27.8 | E18: 2.668248 | F18: =C18-D18 -> -3.9 | G18: 6.14 | H18: 145.41 | I18: 257.096 | J18: Năm bình thường
... A22: 2020 | B22: 2.865413 | C22: 23.9 | D22: 28.3 | E22: 3.220934 | F22: =C22-D22 -> -4.4 | G22: 5.83 | H22: 163.25 | I22: 346.61574 | J22: Đại dịch COVID-19, tăng trưởng giảm còn 2.87%

Sheet Mô tả biến
A1: Mô tả biến và cách sử dụng (Codebook)
A2: Codebook giúp người đọc hiểu nhanh từng biến, đơn vị, vai trò và cách diễn giải.
A4: Biến | B4: Tên đầy đủ | C4: Đơn vị | D4: Nguồn/Công thức | E4: Vai trò | F4: Cách diễn giải / Lưu ý
A5: Year | B5: Năm quan sát | C5: Năm | D5: Dữ liệu theo năm 2005–2020 | E5: Biến thời gian | F5: Mỗi dòng là một năm của Việt Nam. Không dùng làm biến hồi quy.
A6: GDP_Growth | B6: Tăng trưởng GDP thực | C6: % | D6: FRED/IMF WEO | E6: Biến phụ thuộc (Y) | F6: Biến Y trong mô hình chính. Đo lường tốc độ tăng trưởng kinh tế hằng năm.
A7: Balance_GDP | B7: Cân đối ngân sách/GDP | C7: % GDP | D7: Revenue_GDP - Expenditure_GDP | E7: Biến độc lập (X1) | F7: Số âm thể hiện bội chi; số dương thể hiện thặng dư. β1 > 0 nghĩa là cân đối tốt hơn đi kèm tăng trưởng cao hơn.
A8: Inflation | B8: Lạm phát CPI | C8: % | D8: FRED/World Bank/IMF IFS | E8: Biến kiểm soát (X2) | F8: Lạm phát cao thường đi kèm bất ổn vĩ mô. Năm 2008 (23.1%) và 2011 (18.7%) là điểm bất thường.
A9: FDI_GDP | B9: Tỷ lệ FDI ròng/GDP | C9: % GDP | D9: World Bank BX.KLT.DINV.WD.GD.ZS | E9: Biến độc lập bổ sung (X3) | F9: Đo dòng vốn FDI ròng vào nền kinh tế. β3 dự kiến > 0: FDI cao thúc đẩy tăng trưởng.
A10: Trade_Openness | B10: Độ mở thương mại = (X+M)/GDP | C10: % GDP | D10: World Bank NE.TRD.GNFS.ZS | E10: Biến độc lập bổ sung (X4) | F10: Đo mức độ hội nhập kinh tế. Việt Nam là nền kinh tế mở (~130-165% GDP), β4 dự kiến > 0.
A11: Revenue_GDP | B11: Thu NSNN/GDP | C11: % GDP | D11: IMF WEO + World Bank MPO | E11: Biến tham khảo | F11: Không trực tiếp trong mô hình mở rộng; dùng để tính Balance_GDP.
A12: Expenditure_GDP | B12: Chi NSNN/GDP | C12: % GDP | D12: IMF WEO + World Bank MPO | E12: Biến tham khảo | F12: Không trực tiếp trong mô hình mở rộng; dùng để tính Balance_GDP.
A13: GDP_Current_USD_bn | B13: GDP hiện hành | C13: Tỷ USD | D13: FRED/World Bank | E13: Biến quy mô | F13: Dùng để ước tính giá trị tuyệt đối; không dùng trong mô hình chính.

Sheet Thống kê mô tả
A1: Thống kê mô tả các biến
A2: Tất cả các chỉ tiêu sử dụng công thức Excel tham chiếu từ sheet Data_2005_2020 (16 quan sát: 2005–2020).
A4: Biến | B4: Mô tả | C4: N | D4: Trung bình | E4: Độ lệch chuẩn | F4: Nhỏ nhất | G4: Lớn nhất | H4: Đơn vị
A5: GDP_Growth | B5: Tăng trưởng GDP thực | C5: =COUNT(Data_2005_2020!$B$7:$B$22) -> 16 | D5: =AVERAGE(Data_2005_2020!$B$7:$B$22) -> 6.3336346 | E5: =STDEV(Data_2005_2020!$B$7:$B$22) -> 1.1675943 | F5: =MIN(Data_2005_2020!$B$7:$B$22) -> 2.865413 | G5: =MAX(Data_2005_2020!$B$7:$B$22) -> 7.547256 | H5: %
A6: Balance_GDP | B6: Cân đối ngân sách/GDP | C6: =COUNT(Data_2005_2020!$F$7:$F$22) -> 16 | D6: =AVERAGE(Data_2005_2020!$F$7:$F$22) -> -3.533125 | E6: =STDEV(Data_2005_2020!$F$7:$F$22) -> 2.4636361 | F6: =MIN(Data_2005_2020!$F$7:$F$22) -> -7.4 | G6: =MAX(Data_2005_2020!$F$7:$F$22) -> 0.3 | H6: % GDP
A7: Inflation | B7: Lạm phát CPI | C7: =COUNT(Data_2005_2020!$E$7:$E$22) -> 16 | D7: =AVERAGE(Data_2005_2020!$E$7:$E$22) -> 7.3695432 | E7: =STDEV(Data_2005_2020!$E$7:$E$22) -> 5.9492068 | F7: =MIN(Data_2005_2020!$E$7:$E$22) -> 0.631201 | G7: =MAX(Data_2005_2020!$E$7:$E$22) -> 23.115448 | H7: %
A8: FDI_GDP | B8: FDI ròng/GDP | C8: =COUNT(Data_2005_2020!$G$7:$G$22) -> 16 | D8: =AVERAGE(Data_2005_2020!$G$7:$G$22) -> 6.076875 | E8: =STDEV(Data_2005_2020!$G$7:$G$22) -> 1.5850414 | F8: =MIN(Data_2005_2020!$G$7:$G$22) -> 3.39 | G8: =MAX(Data_2005_2020!$G$7:$G$22) -> 9.66 | H8: % GDP
A9: Trade_Openness | B9: Độ mở thương mại | C9: =COUNT(Data_2005_2020!$H$7:$H$22) -> 16 | D9: =AVERAGE(Data_2005_2020!$H$7:$H$22) -> 142.83062 | E9: =STDEV(Data_2005_2020!$H$7:$H$22) -> 16.207882 | F9: =MIN(Data_2005_2020!$H$7:$H$22) -> 113.98 | G9: =MAX(Data_2005_2020!$H$7:$H$22) -> 164.7 | H9: % GDP
A10: Revenue_GDP | B10: Thu NSNN/GDP | C10: =COUNT(Data_2005_2020!$C$7:$C$22) -> 16 | D10: =AVERAGE(Data_2005_2020!$C$7:$C$22) -> 25.346875 | E10: =STDEV(Data_2005_2020!$C$7:$C$22) -> 2.1849721 | F10: =MIN(Data_2005_2020!$C$7:$C$22) -> 22.2 | G10: =MAX(Data_2005_2020!$C$7:$C$22) -> 28.91 | H10: % GDP
A11: Expenditure_GDP | B11: Chi NSNN/GDP | C11: =COUNT(Data_2005_2020!$D$7:$D$22) -> 16 | D11: =AVERAGE(Data_2005_2020!$D$7:$D$22) -> 28.88 | E11: =STDEV(Data_2005_2020!$D$7:$D$22) -> 1.4991375 | F11: =MIN(Data_2005_2020!$D$7:$D$22) -> 25.9 | G11: =MAX(Data_2005_2020!$D$7:$D$22) -> 31.6 | H11: % GDP

Sheet Tương quan
A1: Ma trận hệ số tương quan (Pearson)
A2: Dùng để kiểm tra mối quan hệ sơ bộ giữa các biến và phát hiện đa cộng tuyến.
B4: GDP_Growth | C4: Balance_GDP | D4: Inflation | E4: FDI_GDP | F4: Trade_Openness
A5: GDP_Growth | B5: 1 | C5: =CORREL(Data_2005_2020!$B$7:$B$22,Data_2005_2020!$F$7:$F$22) -> 0.37176314 | D5: =CORREL(Data_2005_2020!$B$7:$B$22,Data_2005_2020!$E$7:$E$22) -> -0.10702508 | E5: =CORREL(Data_2005_2020!$B$7:$B$22,Data_2005_2020!$G$7:$G$22) -> -0.13129637 | F5: =CORREL(Data_2005_2020!$B$7:$B$22,Data_2005_2020!$H$7:$H$22) -> 0.0077189477
A6: Balance_GDP | B6: =CORREL(Data_2005_2020!$F$7:$F$22,Data_2005_2020!$B$7:$B$22) -> 0.37176314 | C6: 1 | D6: =CORREL(Data_2005_2020!$F$7:$F$22,Data_2005_2020!$E$7:$E$22) -> 0.4582526 | E6: =CORREL(Data_2005_2020!$F$7:$F$22,Data_2005_2020!$G$7:$G$22) -> 0.08705914 | F6: =CORREL(Data_2005_2020!$F$7:$F$22,Data_2005_2020!$H$7:$H$22) -> 0.20220979
A7: Inflation | B7: =CORREL(Data_2005_2020!$E$7:$E$22,Data_2005_2020!$B$7:$B$22) -> -0.10702508 | C7: =CORREL(Data_2005_2020!$E$7:$E$22,Data_2005_2020!$F$7:$F$22) -> 0.4582526 | D7: 1 | E7: =CORREL(Data_2005_2020!$E$7:$E$22,Data_2005_2020!$G$7:$G$22) -> 0.36746493 | F7: =CORREL(Data_2005_2020!$E$7:$E$22,Data_2005_2020!$H$7:$H$22) -> -0.29717484
A8: FDI_GDP | B8: =CORREL(Data_2005_2020!$G$7:$G$22,Data_2005_2020!$B$7:$B$22) -> -0.13129637 | C8: =CORREL(Data_2005_2020!$G$7:$G$22,Data_2005_2020!$F$7:$F$22) -> 0.08705914 | D8: =CORREL(Data_2005_2020!$G$7:$G$22,Data_2005_2020!$E$7:$E$22) -> 0.36746493 | E8: 1 | F8: =CORREL(Data_2005_2020!$G$7:$G$22,Data_2005_2020!$H$7:$H$22) -> 0.34245177
A9: Trade_Openness | B9: =CORREL(Data_2005_2020!$H$7:$H$22,Data_2005_2020!$B$7:$B$22) -> 0.0077189477 | C9: =CORREL(Data_2005_2020!$H$7:$H$22,Data_2005_2020!$F$7:$F$22) -> 0.20220979 | D9: =CORREL(Data_2005_2020!$H$7:$H$22,Data_2005_2020!$E$7:$E$22) -> -0.29717484 | E9: =CORREL(Data_2005_2020!$H$7:$H$22,Data_2005_2020!$G$7:$G$22) -> 0.34245177 | F9: 1
A11: Cách đọc: | B11: |r| > 0.8 là tương quan rất mạnh; 0.5–0.8 mạnh; 0.3–0.5 trung bình; < 0.3 yếu. Nếu hai biến độc lập có |r| > 0.8 cần thận trọng do đa cộng tuyến.

Sheet Hồi quy OLS
A1: Hồi quy OLS – Mô hình mở rộng có FDI_GDP và Trade_Openness
A2: Mô hình: GDP_Growth_t = β0 + β1·Balance_GDP_t + β2·Inflation_t + β3·FDI_GDP_t + β4·Trade_Openness_t + u_t
A4: A. MÔ HÌNH MỞ RỘNG (4 biến độc lập)
A6: Biến | B6: Hệ số (β) | C6: Sai số chuẩn | D6: t-stat | E6: P-value (hai phía) | F6: Mức ý nghĩa | G6: Diễn giải ngắn | I6: Chỉ tiêu | J6: Giá trị
A7: Intercept (β0) | B7: =INDEX(LINEST(Data_2005_2020!$B$7:$B$22,Data_2005_2020!$E$7:$H$22,TRUE(),TRUE()),1,5) -> 11.40859 | C7: =INDEX(LINEST(Data_2005_2020!$B$7:$B$22,Data_2005_2020!$E$7:$H$22,TRUE(),TRUE()),2,5) -> 3.6923164 | D7: =B7/C7 -> 3.0898193 | E7: =TDIST(ABS(D7),16-4-1,2) -> 0.010289384 | F7: =IF(E7<0.01,"***",IF(E7<0.05,"**",IF(E7<0.1,"*",""))) -> ** | G7: Hằng số chặn của mô hình. | I7: Số quan sát (n) | J7: =COUNT(Data_2005_2020!$B$7:$B$22) -> 16
A8: Balance_GDP (β1) | B8: =INDEX(LINEST(Data_2005_2020!$B$7:$B$22,Data_2005_2020!$E$7:$H$22,TRUE(),TRUE()),1,3) -> 0.3328024 | C8: =INDEX(LINEST(Data_2005_2020!$B$7:$B$22,Data_2005_2020!$E$7:$H$22,TRUE(),TRUE()),2,3) -> 0.15843974 | D8: =B8/C8 -> 2.1004983 | E8: =TDIST(ABS(D8),16-4-1,2) -> 0.059548923 | F8: =IF(E8<0.01,"***",IF(E8<0.05,"**",IF(E8<0.1,"*",""))) -> * | G8: Cân đối ngân sách tăng 1 điểm % GDP làm GDP_Growth thay đổi β1 điểm %, các yếu tố khác không đổi. | I8: Số biến độc lập (k) | J8: 4
A9: Inflation (β2) | B9: =INDEX(LINEST(Data_2005_2020!$B$7:$B$22,Data_2005_2020!$E$7:$H$22,TRUE(),TRUE()),1,4) -> -0.11583596 | C9: =INDEX(LINEST(Data_2005_2020!$B$7:$B$22,Data_2005_2020!$E$7:$H$22,TRUE(),TRUE()),2,4) -> 0.078944482 | D9: =B9/C9 -> -1.4673092 | E9: =TDIST(ABS(D9),16-4-1,2) -> 0.17029299 | F9: =IF(E9<0.01,"***",IF(E9<0.05,"**",IF(E9<0.1,"*",""))) | G9: Lạm phát tăng 1 điểm % làm GDP_Growth thay đổi β2 điểm %, các yếu tố khác không đổi. | I9: Bậc tự do dư (n-k-1) | J9: =16-4-1 -> 11
A10: FDI_GDP (β3) | B10: =INDEX(LINEST(Data_2005_2020!$B$7:$B$22,Data_2005_2020!$E$7:$H$22,TRUE(),TRUE()),1,2) -> 0.10890266 | C10: =INDEX(LINEST(Data_2005_2020!$B$7:$B$22,Data_2005_2020!$E$7:$H$22,TRUE(),TRUE()),2,2) -> 0.25067615 | D10: =B10/C10 -> 0.43443566 | E10: =TDIST(ABS(D10),16-4-1,2) -> 0.6723712 | F10: =IF(E10<0.01,"***",IF(E10<0.05,"**",IF(E10<0.1,"*",""))) | G10: FDI/GDP tăng 1 điểm % làm GDP_Growth thay đổi β3 điểm %, các yếu tố khác không đổi. | I10: R-squared | J10: =INDEX(LINEST(Data_2005_2020!$B$7:$B$22,Data_2005_2020!$E$7:$H$22,TRUE(),TRUE()),3,1) -> 0.30203429
A11: Trade_Openness (β4) | B11: =INDEX(LINEST(Data_2005_2020!$B$7:$B$22,Data_2005_2020!$E$7:$H$22,TRUE(),TRUE()),1,1) -> -0.02595559 | C11: =INDEX(LINEST(Data_2005_2020!$B$7:$B$22,Data_2005_2020!$E$7:$H$22,TRUE(),TRUE()),2,1) -> 0.025911419 | D11: =B11/C11 -> -1.0017047 | E11: =TDIST(ABS(D11),16-4-1,2) -> 0.33801252 | F11: =IF(E11<0.01,"***",IF(E11<0.05,"**",IF(E11<0.1,"*",""))) | G11: Độ mở thương mại tăng 1 điểm % làm GDP_Growth thay đổi β4 điểm %, các yếu tố khác không đổi. | I11: Adjusted R-squared | J11: =1-(1-J10)*(COUNT(Data_2005_2020!$B$7:$B$22)-1)/(16-4-1) -> 0.048228584
I12: SE of regression | J12: =INDEX(LINEST(Data_2005_2020!$B$7:$B$22,Data_2005_2020!$E$7:$H$22,TRUE(),TRUE()),3,2) -> 1.1390907
A13: Ký hiệu: | B13: *** p<0.01, ** p<0.05, * p<0.1 (kiểm định t hai phía). | I13: F-statistic | J13: =INDEX(LINEST(Data_2005_2020!$B$7:$B$22,Data_2005_2020!$E$7:$H$22,TRUE(),TRUE()),4,1) -> 1.1900217
I14: Prob (F-statistic) | J14: =FDIST(J13,4,16-4-1) -> 0.36826727
I15: SS Regression | J15: =INDEX(LINEST(Data_2005_2020!$B$7:$B$22,Data_2005_2020!$E$7:$H$22,TRUE(),TRUE()),5,1) -> 6.1763435
A16: B. SO SÁNH VỚI MÔ HÌNH GỐC (chỉ có Revenue_GDP, Expenditure_GDP, Inflation)
A18: Chỉ tiêu | B18: Mô hình gốc (3 biến) | C18: Mô hình mở rộng (4 biến) | D18: Thay đổi | E18: Nhận xét
A19: Số biến độc lập (k) | B19: 3 | C19: 4 | D19: =C19-B19 -> 1 | E19: Mô hình mở rộng thêm FDI_GDP và Trade_Openness; đồng thời thay Revenue/Expenditure bằng Balance_GDP (= Revenue – Expenditure).
A20: Bậc tự do dư | B20: 12 | C20: 11 | D20: =C20-B20 -> -1 | E20: Giảm 1 do thêm 2 biến mới và bớt 1 biến (gộp Revenue, Expenditure thành Balance).
A21: R-squared | B21: =INDEX(LINEST(Data_2005_2020!$B$7:$B$22,Data_2005_2020!$C$7:$E$22,TRUE(),TRUE()),3,1) -> 0.23830038 | C21: =J10 -> 0.30203429 | D21: =C21-B21 -> 0.06373391 | E21: R² tăng phản ánh khả năng giải thích tốt hơn nhờ bổ sung biến vĩ mô FDI và độ mở thương mại.
A22: Adjusted R-squared | B22: =1-(1-INDEX(LINEST(Data_2005_2020!$B$7:$B$22,Data_2005_2020!$C$7:$E$22,TRUE(),TRUE()),3,1))*(COUNT(Data_2005_2020!$B$7:$B$22)-1)/(16-3-1) -> 0.047875481 | C22: =J11 -> 0.048228584 | D22: =C22-B22 -> 0.00035310303 | E22: Adj R² tăng cho thấy phần cải thiện không hoàn toàn đến từ việc thêm biến.
A23: F-statistic | B23: =INDEX(LINEST(Data_2005_2020!$B$7:$B$22,Data_2005_2020!$C$7:$E$22,TRUE(),TRUE()),4,1) -> 1.251414 | C23: =J13 -> 1.1900217 | D23: =C23-B23 -> -0.061392303 | E23: F-statistic chung của mô hình mở rộng.
A24: Prob (F-statistic) | B24: =FDIST(B23,3,16-3-1) -> 0.33464708 | C24: =J14 -> 0.36826727 | D24: =C24-B24 -> 0.033620189 | E24: Nếu Prob(F) < 0.10 mô hình có ý nghĩa thống kê tổng quát ở mức 10%.
A26: C. HƯỚNG DẪN ĐỌC KẾT QUẢ
A27: 1. Ý nghĩa thống kê: Mức ý nghĩa được đánh dấu *** (p<0.01), ** (p<0.05), * (p<0.1). Với 16 quan sát và 4 biến độc lập, bậc tự do dư còn 11, mức 10% (*) là chấp nhận được khi viết báo cáo.
A28: 2. Balance_GDP dự kiến có hệ số dương: cân đối ngân sách cải thiện (bội chi giảm hoặc thặng dư tăng) đi kèm tăng trưởng GDP cao hơn.
A29: 3. Inflation dự kiến có hệ số âm: lạm phát cao làm méo mó hệ thống giá, giảm tăng trưởng thực. Tuy nhiên, hệ số nhỏ và không có ý nghĩa thống kê do biến động lạm phát cũng phản ánh chu kỳ kinh tế.
A30: 4. FDI_GDP và Trade_Openness là kênh tăng trưởng dài hạn theo lý thuyết, nhưng với mẫu nhỏ 16 năm có thể không có ý nghĩa thống kê. Vẫn nên giữ trong mô hình để giảm thiên chệch do biến thiếu (omitted variable bias).
A31: 5. Đa cộng tuyến: Trade_Openness và FDI_GDP đều có xu hướng tăng theo thời gian khi Việt Nam hội nhập sâu hơn — cần đọc ma trận tương quan trước khi giải thích từng hệ số.
A32: 6. Tái lập trong Excel: Data → Data Analysis → Regression; Input Y = Data_2005_2020!B7:B22; Input X = Data_2005_2020!E7:H22 (thứ tự cột: Inflation, Balance_GDP, FDI_GDP, Trade_Openness).
A33: 7. Hạn chế: Mẫu 16 năm là quá ngắn để áp dụng các kiểm định mạnh (Breusch-Godfrey, White heteroskedasticity, Chow break). Năm 2020 (COVID-19) là outlier rất lớn nhưng mô hình không có biến giả để hấp thụ – báo cáo cần nêu rõ.

Sheet Nguồn dữ liệu
A1: Nguồn dữ liệu và ghi chú trích dẫn
A2: Các URL nguồn để tiện kiểm tra/tái lập trong báo cáo.
A4: Nguồn | B4: Dùng cho biến | C4: URL | D4: Ghi chú
A5: FRED / IMF WEO Real GDP growth | B5: GDP_Growth | C5: https://fred.stlouisfed.org/series/VNMNGDPRPCPPPT | D5: Annual percent change; nguồn IMF WEO được FRED trình bày.
A6: FRED / World Bank / IMF IFS Inflation | B6: Inflation | C6: https://fred.stlouisfed.org/series/FPCPITOTLZGVNM | D6: Lạm phát CPI hằng năm cho Việt Nam.
A7: FRED / World Bank GDP current USD | B7: GDP_Current_USD_bn | C7: https://fred.stlouisfed.org/series/MKTGDPVNA646NWDB | D7: GDP giá hiện hành (USD), đã quy đổi sang tỷ USD.
A8: EconStats IMF WEO | B8: Revenue_GDP, Expenditure_GDP 2005–2008 | C8: https://www.econstats.com/weo/CVNM.htm | D8: Tỷ lệ thu/chi tài khóa giai đoạn 2005–2008.
A9: World Bank MPO Selected Indicators | B9: Revenue_GDP, Expenditure_GDP 2009–2020 | C9: https://thedocs.worldbank.org/en/doc/833741613054423131-0500052021/related/mpo-vnm.pdf | D9: Bảng Selected indicators về thu/chi và cân đối ngân sách 2009–2020E.
A10: World Bank WDI – BX.KLT.DINV.WD.GD.ZS | B10: FDI_GDP | C10: https://data.worldbank.org/indicator/BX.KLT.DINV.WD.GD.ZS?locations=VN | D10: FDI net inflows (% of GDP) cho Việt Nam; IMF BoP + WB staff estimates.
A11: World Bank WDI – NE.TRD.GNFS.ZS | B11: Trade_Openness | C11: https://data.worldbank.org/indicator/NE.TRD.GNFS.ZS?locations=VN | D11: Trade (% of GDP) = (Exports + Imports) / GDP.
A12: CEIC / IMF GFS | B12: Đối chiếu định nghĩa | C12: https://www.ceicdata.com/en/vietnam/government-finance-statistics | D12: Nguồn đối chiếu định nghĩa general government revenue/expenditure % GDP.
